jira_client-0.0.10.dist-info/DESCRIPTION.rst
jira_client-0.0.10.dist-info/LICENSE.txt
jira_client-0.0.10.dist-info/METADATA
jira_client-0.0.10.dist-info/RECORD
jira_client-0.0.10.dist-info/WHEEL
jira_client-0.0.10.dist-info/metadata.json
jira_client-0.0.10.dist-info/top_level.txt
jiraclient/__init__.py
jiraclient/_auth.py
jiraclient/_deserialize.py
jiraclient/_error.py
jiraclient/jiraclient.py
jiraclient/models.py
jiraclient/_http/__init__.py
jiraclient/_http/httpclient.py
